scaleway_api/__init__.py
tests/__init__.py
tests/test_request.py
tests/test_urls.py
scaleway_api-0.0.1.dist-info/LICENSE
scaleway_api-0.0.1.dist-info/METADATA
scaleway_api-0.0.1.dist-info/WHEEL
scaleway_api-0.0.1.dist-info/top_level.txt
scaleway_api-0.0.1.dist-info/RECORD
