Metadata-Version: 2.1
Name: scaleway-api
Version: 0.0.1
Summary: An unofficial wrapper around the Scaleway APIs based on Hammock.
Home-page: https://github.com/jonathanbaugh/scaleway-api
Author: Jonathan Baugh
Author-email: jonathanatx@gmail.com
License: UNKNOWN
Platform: UNKNOWN
Classifier: Programming Language :: Python :: 3
Classifier: License :: OSI Approved :: MIT License
Classifier: Operating System :: OS Independent
Requires-Python: >=3.6
Requires-Dist: hammock (>=0.2.4)
